tests/__init__.py
tests/test_parser.py
text_in_parser_engine/__init__.py
text_in_parser_engine/text_in_parser_engine.py
text_in_parser_engine-0.1.4.dist-info/METADATA
text_in_parser_engine-0.1.4.dist-info/WHEEL
text_in_parser_engine-0.1.4.dist-info/top_level.txt
text_in_parser_engine-0.1.4.dist-info/RECORD
